{
  "2024-March": [
    {
      "name": "Jennifer Lee",
      "amount": 350
    }
  ],
  "2023-December": [
    {
      "name": "Michael Johnson",
      "amount": 800
    },
    {
      "name": "Amanda Davis",
      "amount": 400
    },
    {
      "name": "Chris Wilson",
      "amount": 550
    }
  ],
  "2023-November": [
    {
      "name": "Jessica Brown",
      "amount": 275
    },
    {
      "name": "Daniel Miller",
      "amount": 625
    }
  ],
  "2022-November": [
    {
      "name": "Jessica Brown",
      "amount": 275
    },
    {
      "name": "Daniel Miller",
      "amount": 625
    }
  ],
  "2021-November": [
    {
      "name": "Jessica Brown",
      "amount": 275
    },
    {
      "name": "Daniel Miller",
      "amount": 625
    }
  ],
  "2020-November": [
    {
      "name": "Jessica Brown",
      "amount": 275
    },
    {
      "name": "Daniel Miller",
      "amount": 625
    }
  ],
  "2025-February": [
    {
      "name": "aaaaaaaaaaaaaaaaaaaa",
      "amount": 6
    },
    {
      "name": "bbbb",
      "amount": 200
    }
  ]
}